README.rst
setup.py
dsfp/__init__.py
dsfp/constants.py
dsfp/dsfp.py
dsfp/exceptions.py
dsfp/tools.py
dsfp/utils.py
dsfp.egg-info/PKG-INFO
dsfp.egg-info/SOURCES.txt
dsfp.egg-info/dependency_links.txt
dsfp.egg-info/not-zip-safe
dsfp.egg-info/requires.txt
dsfp.egg-info/top_level.txt