Metadata-Version: 1.1
Name: dsfp
Version: 0.0.1
Summary: Darksouls Save File Parser for fetching data issues
Home-page: UNKNOWN
Author: Nickolas Fox <tarvitz@blacklibrary.ru>
Author-email: tarvitz@blacklibrary.ru
License: MIT license
Download-URL: https://github.com/tarvitz/dsfp/archive/master.zip
Platform: OS Independent
Classifier: Development Status :: 2 - Pre-Alpha
Classifier: Environment :: Console
Classifier: Intended Audience :: Developers
Classifier: License :: OSI Approved :: MIT License
Classifier: Operating System :: OS Independent
Classifier: Programming Language :: Python
Classifier: Natural Language :: English
Classifier: Topic :: Utilities
